hypermodern_python/__init__.py
hypermodern_python/console.py
hypermodern_python/wikipedia.py
hypermodern_python-0.2.2.dist-info/entry_points.txt
hypermodern_python-0.2.2.dist-info/LICENSE
hypermodern_python-0.2.2.dist-info/WHEEL
hypermodern_python-0.2.2.dist-info/METADATA
hypermodern_python-0.2.2.dist-info/RECORD
